README.rst
setup.py
abstrys/__init__.py
abstrys/app_settings.py
abstrys_core.egg-info/PKG-INFO
abstrys_core.egg-info/SOURCES.txt
abstrys_core.egg-info/dependency_links.txt
abstrys_core.egg-info/namespace_packages.txt
abstrys_core.egg-info/top_level.txt