Metadata-Version: 2.1
Name: abstrys-core
Version: 0.1.1
Summary: Core modules for Abstrys command-line applications
Home-page: https://github.com/Abstrys/abstrys-core/
Author: Eron Hennessey
Author-email: eron@abstrys.com
License: BSD
Keywords: python module
Platform: UNKNOWN
Classifier: Development Status :: 3 - Alpha
Classifier: Topic :: Utilities
Classifier: License :: OSI Approved :: BSD License
